{
    "corrections": {
        "Benchle": "Benchley",
        "Benchle's": "Benchley's",
        "Benchle s": "Benchley's",
        "Benchleyys": "Benchleys",
        "Benchleyy": "Benchley",
        "Benchleyy's": "Benchley's",
        "Benchleyy ": "Benchley ",
        "word ond": "word and",
        "odmirably": "admirably",
        "rereserve": "reserve",
        "serve": "reserve",
        "fallow": "fellow",
        "Jest": "lest",
        "seftle": "settle",
        "isiquite": "is quite",
        "is quite": "is quite",
        "ypper": "upper",
        "resdlve": "resolve",
        "tendericie": "tendencies",
        "bar rd": "barely",
        "only bar": "only barely",
        "onlybarely": "only barely",
        "barelyely": "barely",
        "barelyely-": "barely. ",
        "barelyely ": "barely ",
        "  ": " ",
        " -": "-",
        "- ": "-"
    },
    "priority_order": ["rereserve", "Benchleyys", "Benchleyy's", "Benchleyy "]
}
